{
  "project_info": {
    "project_number": "14891041818",
    "project_id": "heartbeat-music-de491",
    "storage_bucket": "heartbeat-music-de491.firebasestorage.app"
  },
  "client": [
    {
      "client_info": {
        "mobilesdk_app_id": "1:14891041818:android:5e81656fe062bcd4707da3",
        "android_client_info": {
          "package_name": "com.heartbeatmusic"
        }
      },
      "oauth_client": [],
      "api_key": [
        {
          "current_key": "AIzaSyAtBsvd9FIyfAaqahmZ4tJqoU5HAnv5r5s"
        }
      ],
      "services": {
        "appinvite_service": {
          "other_platform_oauth_client": []
        }
      }
    }
  ],
  "configuration_version": "1"
}